vers/__init__.py
vers/chat/__init__.py
vers/chat/respond.py
vers/chat/system.py
vers/flow.py
vers/py.typed
vers/runner.py
vers/task.py
vers/types/__init__.py
vers/types/flows.py
vers/types/llm.py
vers/types/media.py
vers/types/tasks.py
vers_py-0.1.0.dist-info/METADATA
vers_py-0.1.0.dist-info/WHEEL
vers_py-0.1.0.dist-info/RECORD
